aup3conv-0.1.1.dist-info/METADATA
aup3conv-0.1.1.dist-info/WHEEL
aup3conv-0.1.1.dist-info/licenses/LICENSE
aup3conv/__init__.py
aup3conv/py.typed
aup3conv/aup3conv.pyi
aup3conv/_aup3conv.cpython-311-darwin.so
aup3conv-0.1.1.dist-info/RECORD
