Metadata-Version: 2.4
Name: aup3conv
Version: 0.1.1
Classifier: Development Status :: 3 - Alpha
Classifier: Intended Audience :: Information Technology
Classifier: Intended Audience :: Science/Research
Classifier: License :: OSI Approved :: BSD License
Classifier: Operating System :: POSIX
Classifier: Programming Language :: Python :: 3 :: Only
Classifier: Programming Language :: Python :: 3.11
Classifier: Programming Language :: Python :: 3.12
Classifier: Programming Language :: Python :: 3.13
Classifier: Programming Language :: Python :: Implementation :: CPython
Classifier: Programming Language :: Python :: Implementation :: PyPy
Classifier: Programming Language :: Rust
Classifier: Topic :: Multimedia :: Sound/Audio :: Conversion
Classifier: Topic :: Multimedia :: Sound/Audio
License-File: LICENSE
Summary: Scrape Audacity project files
Keywords: audio,analysis,audacity,parsing
Author-email: Michael Blaß <m.blass@uke.de>
License: LICENSE
Requires-Python: >=3.11
Project-URL: source, https://github.com/UKEIAM/aup3conv
